openg2p_g2pconnect_mapper_lib/__init__.py
openg2p_g2pconnect_mapper_lib/app.py
openg2p_g2pconnect_mapper_lib/config.py
openg2p_g2pconnect_mapper_lib/client/__init__.py
openg2p_g2pconnect_mapper_lib/client/link.py
openg2p_g2pconnect_mapper_lib/client/resolve.py
openg2p_g2pconnect_mapper_lib/client/unlink.py
openg2p_g2pconnect_mapper_lib/client/update.py
openg2p_g2pconnect_mapper_lib/schemas/__init__.py
openg2p_g2pconnect_mapper_lib/schemas/link.py
openg2p_g2pconnect_mapper_lib/schemas/resolve.py
openg2p_g2pconnect_mapper_lib/schemas/txnstatus.py
openg2p_g2pconnect_mapper_lib/schemas/unlink.py
openg2p_g2pconnect_mapper_lib/schemas/update.py
openg2p_g2pconnect_mapper_lib-2.0.0.dist-info/METADATA
openg2p_g2pconnect_mapper_lib-2.0.0.dist-info/WHEEL
openg2p_g2pconnect_mapper_lib-2.0.0.dist-info/RECORD
