Metadata-Version: 2.4
Name: openg2p-g2pconnect-mapper-lib
Version: 2.0.0
Summary: OpenG2P Common Library for G2PConnect ID Mapper.
Project-URL: Homepage, https://openg2p.org
Project-URL: Documentation, https://docs.openg2p.org/
Project-URL: Repository, https://github.com/OpenG2P/openg2p-g2pconnect-common
Author-email: OpenG2P <info@openg2p.org>
Classifier: License :: OSI Approved :: Mozilla Public License 2.0 (MPL 2.0)
Classifier: Operating System :: OS Independent
Classifier: Programming Language :: Python :: 3
Requires-Python: >=3.7
Requires-Dist: openg2p-g2pconnect-common-lib
